blender_notebook/__init__.py
blender_notebook/installer.py
blender_notebook/kernel.py
blender_notebook/kernel_launcher.py
blender_notebook-0.0.4.dist-info/METADATA
blender_notebook-0.0.4.dist-info/WHEEL
blender_notebook-0.0.4.dist-info/entry_points.txt
blender_notebook-0.0.4.dist-info/licenses/LICENSE
blender_notebook-0.0.4.dist-info/RECORD
