Metadata-Version: 2.4
Name: blender_notebook
Version: 0.0.4
Summary: A simple command line tool to wrap blender 2.8+ as a jupyter kernel
Author-email: Cheng Chi <cheng-chi@outlook.com>, Jan-Hendrik Müller <jan-hendrik.mueller@gmx.net>
License: MIT
License-File: LICENSE
Classifier: Intended Audience :: Developers
Classifier: Programming Language :: Python
Classifier: Programming Language :: Python :: 3
Classifier: Programming Language :: Python :: 3.11
Requires-Python: >=3.10
Requires-Dist: click
Requires-Dist: ipykernel
Requires-Dist: notebook
